metafile_sdk/__init__.py
metafile_sdk/cache_model.py
metafile_sdk/hash_func.py
metafile_sdk/metafile.py
metafile_sdk/orm.py
metafile_sdk/transaction.py
metafile_sdk/utils.py
metafile_sdk/version.py
metafile_sdk/api/__init__.py
metafile_sdk/api/api_base.py
metafile_sdk/api/metafile.py
metafile_sdk/api/metasv.py
metafile_sdk/api/sensible_query.py
metafile_sdk/api/showmandb.py
metafile_sdk/api/woc.py
metafile_sdk/bitsv/__init__.py
metafile_sdk/bitsv/base58.py
metafile_sdk/bitsv/cli.py
metafile_sdk/bitsv/constants.py
metafile_sdk/bitsv/crypto.py
metafile_sdk/bitsv/curve.py
metafile_sdk/bitsv/exceptions.py
metafile_sdk/bitsv/format.py
metafile_sdk/bitsv/keygen.py
metafile_sdk/bitsv/op_return.py
metafile_sdk/bitsv/transaction.py
metafile_sdk/bitsv/utils.py
metafile_sdk/bitsv/wallet.py
metafile_sdk/bitsv/network/__init__.py
metafile_sdk/bitsv/network/fees.py
metafile_sdk/bitsv/network/meta.py
metafile_sdk/bitsv/network/rates.py
metafile_sdk/bitsv/network/transaction.py
metafile_sdk/bitsv/network/services/__init__.py
metafile_sdk/bitsv/network/services/bsvbookguarda.py
metafile_sdk/bitsv/network/services/fullnode.py
metafile_sdk/bitsv/network/services/mattercloud.py
metafile_sdk/bitsv/network/services/network.py
metafile_sdk/bitsv/network/services/standardrpcmethods.py
metafile_sdk/bitsv/network/services/whatsonchain.py
metafile_sdk/model/__init__.py
metafile_sdk/model/base.py
metafile_sdk-0.3.3.dist-info/LICENSE
metafile_sdk-0.3.3.dist-info/METADATA
metafile_sdk-0.3.3.dist-info/WHEEL
metafile_sdk-0.3.3.dist-info/top_level.txt
metafile_sdk-0.3.3.dist-info/RECORD
