Metadata-Version: 2.1
Name: metafile-sdk
Version: 0.3.3
Summary: Metafile Python SDK
Home-page: https://github.com/xiangpengm/metafile-sdk-py
Author: https://github.com/xiangpengm
Author-email: xiangpeng@metafile.id
Project-URL: Bug Tracker, https://github.com/xiangpengm/metafile-sdk-py/issues
Classifier: Programming Language :: Python :: 3
Classifier: License :: OSI Approved :: MIT License
Classifier: Operating System :: OS Independent
Requires-Python: >=3.6
License-File: LICENSE
Requires-Dist: bitsv >=0.11.5
Requires-Dist: pydantic >=1.8.2
Requires-Dist: requests >=2.26.0
Requires-Dist: SQLAlchemy >=1.4.26
